MANIFEST.in
README.md
setup.py
colour_segmentation/segmentator.py
colour_segmentation.egg-info/PKG-INFO
colour_segmentation.egg-info/SOURCES.txt
colour_segmentation.egg-info/dependency_links.txt
colour_segmentation.egg-info/requires.txt
colour_segmentation.egg-info/top_level.txt
colour_segmentation/__pycache__/segmentator.cpython-38.pyc
colour_segmentation/algorithms/fuzzy_sets/amante_trapezoidal_segmentator.py
colour_segmentation/algorithms/fuzzy_sets/chamorro_trapezoidal_segmentator.py
colour_segmentation/algorithms/fuzzy_sets/liu_wang_trapezoidal_segmentator.py
colour_segmentation/algorithms/fuzzy_sets/shamir_triangular_segmentator.py
colour_segmentation/algorithms/fuzzy_sets/__pycache__/amante_trapezoidal_segmentator.cpython-38.pyc
colour_segmentation/algorithms/fuzzy_sets/__pycache__/chamorro_trapezoidal_segmentator.cpython-38.pyc
colour_segmentation/algorithms/fuzzy_sets/__pycache__/liu_wang_trapezoidal_segmentator.cpython-38.pyc
colour_segmentation/algorithms/fuzzy_sets/__pycache__/shamir_triangular_segmentator.cpython-38.pyc
colour_segmentation/base/segmentation_algorithm.py
colour_segmentation/base/segmentation_result.py
colour_segmentation/base/__pycache__/segmentation_algorithm.cpython-38.pyc
colour_segmentation/base/__pycache__/segmentation_result.cpython-38.pyc
colour_segmentation/base/algorithms/fuzzy_set_segmentator.py
colour_segmentation/base/algorithms/__pycache__/fuzzy_set_segmentator.cpython-38.pyc
colour_segmentation/base/exceptions/fuzzy_palette_invalid_representation.py
colour_segmentation/docs/colour_segmentation_logo.png