Metadata-Version: 1.0
Name: colour-segmentation
Version: 1.9
Summary: Set of algorithms for the color segmentation of an image
Home-page: https://github.com/mmunar97/colour-segmentation
Author: marcmunar
Author-email: marc.munar@uib.es
License: mit
Platform: UNKNOWN
